pylsp_mypy/__init__.py
pylsp_mypy/_version.py
pylsp_mypy/plugin.py
pylsp_mypy-0.6.8.dist-info/LICENSE
pylsp_mypy-0.6.8.dist-info/METADATA
pylsp_mypy-0.6.8.dist-info/WHEEL
pylsp_mypy-0.6.8.dist-info/entry_points.txt
pylsp_mypy-0.6.8.dist-info/top_level.txt
pylsp_mypy-0.6.8.dist-info/RECORD
