Metadata-Version: 2.1
Name: pylsp-mypy
Version: 0.6.8
Summary: Mypy linter for the Python LSP Server
Home-page: https://github.com/python-lsp/pylsp-mypy
Author: Richard Kellnberger, Tom van Ommeren
License: 'MIT'
Classifier: Development Status :: 4 - Beta
Classifier: Intended Audience :: Developers
Classifier: Topic :: Software Development
Classifier: License :: OSI Approved :: MIT License
Classifier: Programming Language :: Python :: 3.7
Classifier: Programming Language :: Python :: 3.8
Classifier: Programming Language :: Python :: 3.9
Classifier: Programming Language :: Python :: 3.10
Classifier: Programming Language :: Python :: 3.11
Requires-Python: >=3.8
License-File: LICENSE
Requires-Dist: python-lsp-server>=1.7.0
Requires-Dist: mypy>=0.981
Requires-Dist: tomli>=1.1.0
Provides-Extra: test
Requires-Dist: tox; extra == "test"
Requires-Dist: pytest; extra == "test"
Requires-Dist: pytest-cov; extra == "test"
Requires-Dist: coverage; extra == "test"
